hydra.py
hydra_ui-1.1.0.dist-info/METADATA
hydra_ui-1.1.0.dist-info/WHEEL
hydra_ui-1.1.0.dist-info/top_level.txt
hydra_ui-1.1.0.dist-info/RECORD
